LangChainAgentFactory/AgentFactory.py
LangChainAgentFactory/__init__.py
LangChainAgentFactory-0.3.dist-info/LICENSE.txt
LangChainAgentFactory-0.3.dist-info/METADATA
LangChainAgentFactory-0.3.dist-info/WHEEL
LangChainAgentFactory-0.3.dist-info/top_level.txt
LangChainAgentFactory-0.3.dist-info/RECORD
