Metadata-Version: 2.1
Name: LangChainAgentFactory
Version: 0.3
Summary: A wrapper for LangChain to create AI Agents with Open AI LLMs
Author-email: Kenny Dubroff <kennydubroff@devgauge.com>
Project-URL: Source, https://github.com/DevGauge/LangChainAgentFactory/archive/refs/tags/0.3.zip
Classifier: Development Status :: 3 - Alpha
Classifier: License :: OSI Approved :: MIT License
Classifier: Programming Language :: Python :: 3.8
Classifier: Programming Language :: Python :: 3.9
License-File: LICENSE.txt
Requires-Dist: langchain
Requires-Dist: python-dotenv
